lazy_managers/__init__.py
lazy_managers/attribute.py
lazy_managers/manager.py
lazy_managers/py.typed
lazy_managers/typing.py
lazy_managers/utils.py
django_lazy_managers-0.0.1.dist-info/LICENSE
django_lazy_managers-0.0.1.dist-info/METADATA
django_lazy_managers-0.0.1.dist-info/WHEEL
django_lazy_managers-0.0.1.dist-info/RECORD
