Metadata-Version: 2.3
Name: django-lazy-managers
Version: 0.0.1
Summary: Lazy model managers for Django
License: MIT
Keywords: django,lazy,manager
Author: Matti Lamppu
Author-email: lamppu.matti.akseli@gmail.com
Requires-Python: >=3.11,<4
Classifier: Development Status :: 4 - Beta
Classifier: Environment :: Web Environment
Classifier: Operating System :: OS Independent
Classifier: Intended Audience :: Developers
Classifier: Topic :: Utilities
Classifier: Topic :: Software Development :: Libraries
Classifier: Programming Language :: Python
Classifier: Programming Language :: Python :: 3
Classifier: Programming Language :: Python :: 3 :: Only
Classifier: Programming Language :: Python :: 3.11
Classifier: Programming Language :: Python :: 3.12
Classifier: Programming Language :: Python :: 3.13
Classifier: Framework :: Django
Classifier: Framework :: Django :: 4.2
Classifier: Framework :: Django :: 5.0
Classifier: Framework :: Django :: 5.1
Requires-Dist: Django (>=4.2)
Project-URL: Bug Tracker, https://github.com/MrThearMan/django-lazy-managers/issues
Project-URL: Documentation, https://mrthearman.github.io/django-lazy-managers
Project-URL: Homepage, https://mrthearman.github.io/django-lazy-managers
Project-URL: Repository, https://github.com/MrThearMan/django-lazy-managers
